{
  "biomesoplenty:recipes/transportation/boat_ethereal": {
    "criteria": {
      "entered_water": "2019-04-23 11:55:05 +0200"
    },
    "done": true
  },
  "biomesoplenty:recipes/transportation/boat_mahogany": {
    "criteria": {
      "entered_water": "2019-04-23 11:55:05 +0200"
    },
    "done": true
  },
  "biomesoplenty:recipes/transportation/boat_cherry": {
    "criteria": {
      "entered_water": "2019-04-23 11:55:05 +0200"
    },
    "done": true
  },
  "minecraft:recipes/transportation/dark_oak_boat": {
    "criteria": {
      "entered_water": "2019-04-23 11:55:05 +0200"
    },
    "done": true
  },
  "biomesoplenty:recipes/transportation/boat_jacaranda": {
    "criteria": {
      "entered_water": "2019-04-23 11:55:05 +0200"
    },
    "done": true
  },
  "biomesoplenty:recipes/transportation/boat_umbran": {
    "criteria": {
      "entered_water": "2019-04-23 11:55:05 +0200"
    },
    "done": true
  },
  "astralsorcery:root": {
    "criteria": {
      "astralsorcery_present": "2019-04-23 11:50:05 +0200"
    },
    "done": true
  },
  "minecraft:recipes/building_blocks/stonebrick": {
    "criteria": {
      "has_stone": "2019-04-23 12:08:59 +0200"
    },
    "done": true
  },
  "enderio:root": {
    "criteria": {
      "location": "2019-04-23 11:54:17 +0200"
    },
    "done": true
  },
  "minecraft:adventure/adventuring_time": {
    "criteria": {
      "forest": "2019-04-23 11:53:04 +0200",
      "extreme_hills_with_trees": "2019-04-23 12:40:00 +0200",
      "forest_hills": "2019-04-23 11:50:17 +0200",
      "taiga": "2019-04-23 11:53:02 +0200",
      "extreme_hills": "2019-04-23 11:50:05 +0200",
      "river": "2019-04-23 11:53:28 +0200"
    },
    "done": false
  },
  "biomesoplenty:recipes/transportation/boat_fir": {
    "criteria": {
      "entered_water": "2019-04-23 11:55:05 +0200"
    },
    "done": true
  },
  "biomesoplenty:recipes/transportation/boat_magic": {
    "criteria": {
      "entered_water": "2019-04-23 11:55:05 +0200"
    },
    "done": true
  },
  "biomesoplenty:recipes/transportation/boat_ebony": {
    "criteria": {
      "entered_water": "2019-04-23 11:55:05 +0200"
    },
    "done": true
  },
  "minecraft:recipes/transportation/birch_boat": {
    "criteria": {
      "entered_water": "2019-04-23 11:55:05 +0200"
    },
    "done": true
  },
  "minecraft:recipes/decorations/chest": {
    "criteria": {
      "has_lots_of_items": "2019-04-23 12:22:07 +0200"
    },
    "done": true
  },
  "biomesoplenty:recipes/transportation/boat_hellbark": {
    "criteria": {
      "entered_water": "2019-04-23 11:55:05 +0200"
    },
    "done": true
  },
  "biomesoplenty:recipes/transportation/boat_willow": {
    "criteria": {
      "entered_water": "2019-04-23 11:55:05 +0200"
    },
    "done": true
  },
  "biomesoplenty:recipes/transportation/boat_sacred_oak": {
    "criteria": {
      "entered_water": "2019-04-23 11:55:05 +0200"
    },
    "done": true
  },
  "biomesoplenty:recipes/transportation/boat_mangrove": {
    "criteria": {
      "entered_water": "2019-04-23 11:55:05 +0200"
    },
    "done": true
  },
  "minecraft:recipes/transportation/acacia_boat": {
    "criteria": {
      "entered_water": "2019-04-23 11:55:05 +0200"
    },
    "done": true
  },
  "biomesoplenty:recipes/transportation/boat_pine": {
    "criteria": {
      "entered_water": "2019-04-23 11:55:05 +0200"
    },
    "done": true
  },
  "minecraft:recipes/redstone/stone_button": {
    "criteria": {
      "has_stone": "2019-04-23 12:08:59 +0200"
    },
    "done": true
  },
  "biomesoplenty:recipes/transportation/boat_palm": {
    "criteria": {
      "entered_water": "2019-04-23 11:55:05 +0200"
    },
    "done": true
  },
  "biomesoplenty:recipes/transportation/boat_redwood": {
    "criteria": {
      "entered_water": "2019-04-23 11:55:05 +0200"
    },
    "done": true
  },
  "minecraft:recipes/building_blocks/stone_slab": {
    "criteria": {
      "has_stone": "2019-04-23 12:08:59 +0200"
    },
    "done": true
  },
  "minecraft:recipes/redstone/stone_pressure_plate": {
    "criteria": {
      "has_stone": "2019-04-23 12:08:59 +0200"
    },
    "done": true
  },
  "minecraft:recipes/transportation/boat": {
    "criteria": {
      "entered_water": "2019-04-23 11:55:05 +0200"
    },
    "done": true
  },
  "biomesoplenty:recipes/transportation/boat_eucalyptus": {
    "criteria": {
      "entered_water": "2019-04-23 11:55:05 +0200"
    },
    "done": true
  },
  "minecraft:recipes/transportation/jungle_boat": {
    "criteria": {
      "entered_water": "2019-04-23 11:55:05 +0200"
    },
    "done": true
  },
  "minecraft:recipes/transportation/spruce_boat": {
    "criteria": {
      "entered_water": "2019-04-23 11:55:05 +0200"
    },
    "done": true
  }
}